xontrib/goenv.py
xontrib/langenv_common.py
xontrib/nodenv.py
xontrib/pyenv.py
xontrib/rbenv.py
xontrib_langenv-1.2.2.dist-info/LICENSE.txt
xontrib_langenv-1.2.2.dist-info/METADATA
xontrib_langenv-1.2.2.dist-info/WHEEL
xontrib_langenv-1.2.2.dist-info/RECORD
