Metadata-Version: 2.1
Name: xontrib-langenv
Version: 1.2.2
Summary: Pyenv/Nodenv/Goenv/Rbenv integration for xonsh
Home-page: https://github.com/dyuri/xontrib-langenv
License: MIT
Author: Gyuri Horak
Author-email: dyuri@horak.hu
Requires-Python: >=3.8,<4.0
Classifier: Environment :: Console
Classifier: License :: OSI Approved :: MIT License
Classifier: Programming Language :: Python
Classifier: Programming Language :: Python :: 3
Classifier: Programming Language :: Python :: 3.8
Classifier: Programming Language :: Python :: 3.9
Classifier: Programming Language :: Python :: 3.10
Classifier: Programming Language :: Python :: 3.11
Classifier: Programming Language :: Python :: 3.12
Classifier: Topic :: System :: Shells
Classifier: Topic :: System :: System Shells
Project-URL: Repository, https://github.com/dyuri/xontrib-langenv
